DotMeme/__init__.py
DotMeme-0.2.3.dist-info/LICENSE
DotMeme-0.2.3.dist-info/METADATA
DotMeme-0.2.3.dist-info/WHEEL
DotMeme-0.2.3.dist-info/top_level.txt
DotMeme-0.2.3.dist-info/RECORD
