Metadata-Version: 2.1
Name: DotMeme
Version: 0.2.3
Summary: A package to use .meme files
Home-page: https://gitlab.com/ire4ever1190/dotmeme
Author: Jake Leahy
Author-email: darhyaust@gmail.com
License: UNKNOWN
Platform: UNKNOWN
Classifier: Programming Language :: Python :: 3
Classifier: License :: OSI Approved :: MIT License
Classifier: Operating System :: OS Independent
Requires-Dist: Pillow
Requires-Dist: pyyaml
Requires-Dist: requests
